jupyterlab_genv/__init__.py
jupyterlab_genv/__main__.py
jupyterlab_genv/_version.py
jupyterlab_genv/genv_provisioner.py
jupyterlab_genv/handlers.py
jupyterlab_genv/genv/__init__.py
jupyterlab_genv/genv/control.py
jupyterlab_genv/genv/devices.py
jupyterlab_genv/genv/envs.py
jupyterlab_genv/labextension/build_log.json
jupyterlab_genv/labextension/install.json
jupyterlab_genv/labextension/package.json
jupyterlab_genv/labextension/static/lib_index_js.535c840e419a7983feec.js
jupyterlab_genv/labextension/static/lib_index_js.535c840e419a7983feec.js.map
jupyterlab_genv/labextension/static/remoteEntry.69c04a21e698bce9becb.js
jupyterlab_genv/labextension/static/remoteEntry.69c04a21e698bce9becb.js.map
jupyterlab_genv/labextension/static/style.js
jupyterlab_genv/labextension/static/style_index_js.a3066ab30c6e44a6f59d.js
jupyterlab_genv/labextension/static/style_index_js.a3066ab30c6e44a6f59d.js.map
jupyterlab_genv/labextension/static/vendors-node_modules_css-loader_dist_runtime_api_js-node_modules_css-loader_dist_runtime_cssW-72eba1.ba343de920bfc21e5495.js
jupyterlab_genv/labextension/static/vendors-node_modules_css-loader_dist_runtime_api_js-node_modules_css-loader_dist_runtime_cssW-72eba1.ba343de920bfc21e5495.js.map
jupyterlab_genv-0.4.0.data/data/etc/jupyter/jupyter_notebook_config.d/jupyterlab_genv.json
jupyterlab_genv-0.4.0.data/data/etc/jupyter/jupyter_server_config.d/jupyterlab_genv.json
jupyterlab_genv-0.4.0.data/data/share/jupyter/labextensions/jupyterlab_genv/build_log.json
jupyterlab_genv-0.4.0.data/data/share/jupyter/labextensions/jupyterlab_genv/install.json
jupyterlab_genv-0.4.0.data/data/share/jupyter/labextensions/jupyterlab_genv/package.json
jupyterlab_genv-0.4.0.data/data/share/jupyter/labextensions/jupyterlab_genv/static/lib_index_js.535c840e419a7983feec.js
jupyterlab_genv-0.4.0.data/data/share/jupyter/labextensions/jupyterlab_genv/static/lib_index_js.535c840e419a7983feec.js.map
jupyterlab_genv-0.4.0.dist-info/METADATA
jupyterlab_genv-0.4.0.dist-info/WHEEL
jupyterlab_genv-0.4.0.dist-info/entry_points.txt
jupyterlab_genv-0.4.0.dist-info/licenses/LICENSE
jupyterlab_genv-0.4.0.dist-info/RECORD
