Metadata-Version: 2.1
Name: jupyterlab_genv
Version: 0.4.0
Summary: A JupyterLab extension for managing GPU environments using genv.
Project-URL: Homepage, https://github.com/run-ai/jupyterlab_genv
Author-email: Raz Rotenberg <raz.rotenberg@gmail.com>
License: BSD 3-Clause License
License-File: LICENSE
Keywords: Jupyter,JupyterLab,JupyterLab3
Classifier: Framework :: Jupyter
Classifier: Framework :: Jupyter :: JupyterLab
Classifier: Framework :: Jupyter :: JupyterLab :: 3
Classifier: Framework :: Jupyter :: JupyterLab :: Extensions
Classifier: Framework :: Jupyter :: JupyterLab :: Extensions :: Prebuilt
Classifier: License :: OSI Approved :: BSD License
Classifier: Programming Language :: Python
Classifier: Programming Language :: Python :: 3
Classifier: Programming Language :: Python :: 3.7
Classifier: Programming Language :: Python :: 3.8
Classifier: Programming Language :: Python :: 3.9
Classifier: Programming Language :: Python :: 3.10
Requires-Python: >=3.7
Requires-Dist: genv
Requires-Dist: jupyter-server<3,>=1.6
Provides-Extra: test
